LICENSE
pyshelltest/__init__.py
pyshelltest-0.8.3.dist-info/LICENSE
pyshelltest-0.8.3.dist-info/WHEEL
pyshelltest-0.8.3.dist-info/METADATA
pyshelltest-0.8.3.dist-info/RECORD
