Metadata-Version: 2.1
Name: pyshelltest
Version: 0.8.3
Summary: Generate test cases for shell scripts
Home-page: https://github.com/bnichs/pyshelltest.git
License: MIT
Keywords: generation,test,case
Author: Ben
Author-email: bnichs55@gmail.com
Requires-Python: >=3.7,<4.0
Classifier: Development Status :: 3 - Alpha
Classifier: Environment :: Console
Classifier: Intended Audience :: Developers
Classifier: License :: OSI Approved :: MIT License
Classifier: Operating System :: OS Independent
Classifier: Programming Language :: Python :: 3
Classifier: Programming Language :: Python :: 3.7
Classifier: Programming Language :: Python :: 3.8
Classifier: Programming Language :: Python :: 3.9
Classifier: Programming Language :: Python :: 3.10
Classifier: Programming Language :: Python :: 3
Classifier: Topic :: Software Development :: Testing
Classifier: Topic :: System :: Shells
Requires-Dist: attrs (==19.2.0)
Requires-Dist: flake8 (>=4.0.1,<5.0.0)
Requires-Dist: pytest (>=6.2.5,<7.0.0)
Requires-Dist: pytest-cov (>=3.0.0,<4.0.0)
Requires-Dist: toml (>=0.10.2,<0.11.0)
Project-URL: Repository, https://github.com/bnichs/pyshelltest.git
